viur/assistant/__init__.py
viur/assistant/config.py
viur/assistant/version.py
viur/assistant/bones/__init__.py
viur/assistant/bones/actions.py
viur/assistant/bones/image.py
viur/assistant/modules/__init__.py
viur/assistant/modules/assistant.py
viur/assistant/skeletons/__init__.py
viur/assistant/skeletons/assistant.py
viur_assistant-1.2.0.dist-info/licenses/LICENSE
viur_assistant-1.2.0.dist-info/METADATA
viur_assistant-1.2.0.dist-info/WHEEL
viur_assistant-1.2.0.dist-info/top_level.txt
viur_assistant-1.2.0.dist-info/RECORD
