Metadata-Version: 2.4
Name: viur-assistant
Version: 1.2.0
Summary: AI-based assistance module plugin for ViUR
Author-email: "Andreas H. Kelch" <ak@mausbrand.de>, Sven Eberth <se@mausbrand.de>
Maintainer-email: Sven Eberth <se@mausbrand.de>
License: MIT License
Project-URL: Repository, https://github.com/viur-framework/viur-assistant.git
Project-URL: Bug Tracker, https://github.com/viur-framework/viur-assistant/issues
Keywords: viur,plugin,backend,ai,assistant
Classifier: Development Status :: 5 - Production/Stable
Classifier: Intended Audience :: Developers
Classifier: License :: OSI Approved :: MIT License
Classifier: Operating System :: OS Independent
Classifier: Programming Language :: Python :: 3
Classifier: Topic :: Software Development :: Libraries :: Python Modules
Requires-Python: >=3.11
License-File: LICENSE
Requires-Dist: viur-core>=3.7.0
Requires-Dist: anthropic~=0.52
Requires-Dist: openai~=1.82
Provides-Extra: testing
Requires-Dist: pycodestyle; extra == "testing"
Requires-Dist: pytest; extra == "testing"
Dynamic: license-file
